dasladen/__init__.py
dasladen/__main__.py
dasladen/base.py
dasladen/compat.py
dasladen/log.py
dasladen/processor.py
dasladen/task.py
dasladen/taskdriver.py
dasladen/taskrun.py
dasladen/util/__init__.py
dasladen/util/empty_as_null.py
dasladen/util/sanitize_string.py
dasladen-0.2.1.dist-info/LICENSE.txt
dasladen-0.2.1.dist-info/METADATA
dasladen-0.2.1.dist-info/WHEEL
dasladen-0.2.1.dist-info/entry_points.txt
dasladen-0.2.1.dist-info/top_level.txt
dasladen-0.2.1.dist-info/RECORD
