Metadata-Version: 2.1
Name: dasladen
Version: 0.2.1
Summary: Simple, tiny and ridiculus ETL made with Python
Home-page: https://github.com/pagotti/dasladen
Author: Vagner Pagotti
Author-email: pagotti@gmail.com
License: MIT License
Keywords: etl
Platform: UNKNOWN
Classifier: Development Status :: 3 - Alpha
Classifier: Intended Audience :: Developers
Classifier: License :: OSI Approved :: MIT License
Classifier: Programming Language :: Python :: 2
Classifier: Programming Language :: Python :: 2.7
Classifier: Programming Language :: Python :: 3
Classifier: Programming Language :: Python :: 3.7
Classifier: Topic :: Software Development :: Libraries :: Python Modules
Requires-Dist: schedule
Requires-Dist: petl
Requires-Dist: backports.tempfile
Requires-Dist: ftputil
Requires-Dist: xlrd
Requires-Dist: xlwt-future
Requires-Dist: requests
